[
  {
    "perfume clicado": "9PM Pour Femme EDP 100ML",
    "Número de eventos": 2
  },
  {
    "perfume clicado": "Armani Sí Tester EDP 100ML",
    "Número de eventos": 2
  },
  {
    "perfume clicado": "9AM Dive EDP 100ML",
    "Número de eventos": 1
  },
  {
    "perfume clicado": "9PM Rebel EDP 100ML",
    "Número de eventos": 1
  },
  {
    "perfume clicado": "Armani Code Tester EDP 75ML",
    "Número de eventos": 1
  },
  {
    "perfume clicado": "My Way Néctar Tester EDP 90ML",
    "Número de eventos": 1
  }
]